{
  "28-06-2020":
  {
    "1": "Dr. No",
    "2": "Goldfinger",
    "3": "Thunderball",
    "4": "You Only Live Twice",
    "5": "Skyfall",
    "6": "Spectre",
    "7": "No Time to Die"
  },
  "29-06-2020":
  {
    "1": "Baby Driver",
    "2": "Fast Five",
    "3": "The Bank Job",
    "4": "Inside Man",
    "5": "The Italian Job",
    "6": "Ocean's Eleven",
    "7": "The Usual Suspects"
  },
  "30-06-2020":
  {
    "1": "The Ipcress File",
    "2": "Bridge of Spies",
    "3": "Burn After Reading",
    "4": "Mission: Impossible",
    "5": "Enemy of the State",
    "6": "Argo",
    "7": "The Bourne Identity"
  },
  "01-07-2020":
  {
    "1": "Iron Man",
    "2": "Captain America: The First Avenger",
    "3": "Marvel's The Avengers",
    "4": "Iron Man 3",
    "5": "Avengers: Age of Ultron",
    "6": "Avengers: Infinity War",
    "7": "Avengers: Endgame"
  },
  "02-07-2020": {
    "1": "Dr. No",
    "2": "Goldfinger",
    "3": "Thunderball",
    "4": "Bharat",
    "5": "Good Newwz",
    "6": "Mission Mangal",
    "7": "Housefull 4"
  },
  "03-07-2020": {
    "1": "Kalank",
    "2": "Kabir Singh",
    "3": "Saaho",
    "4": "The Sky Is Pink",
    "5": "Ghost",
    "6": "Bypass Road",
    "7": "House Arrest"
  }
}